{
	"class" : {
		"tileWidth:tileHeight:padding:sizeRatio:model:" : "jj 6/23/2024 13:36" },
	"instance" : {
		"brush" : "JS 7/12/2024 16:55",
		"currentTileChanges" : "Valentin Teutschbein 7/12/2024 14:15",
		"currentTileChanges:" : "JS 7/12/2024 21:19",
		"deleteTiles:inLayer:" : "Valentin Teutschbein 7/12/2024 23:35",
		"handlesMouseDown:" : "jj 6/23/2024 13:35",
		"handlesMouseMove:" : "jj 6/23/2024 13:35",
		"handlesMouseOver:" : "Ivo Zilkenat 7/11/2024 17:14",
		"highlightTilesFromIndices:" : "Valentin Teutschbein 7/12/2024 23:35",
		"initialize" : "Ivo Zilkenat 7/12/2024 17:04",
		"model" : "jj 6/23/2024 13:35",
		"model:" : "JS 7/12/2024 21:19",
		"mouseDown:" : "Ivo Zilkenat 7/12/2024 23:39",
		"mouseLeave:" : "JS 7/12/2024 16:27",
		"mouseMove:" : "Ivo Zilkenat 7/12/2024 23:39",
		"mouseUp:" : "Ivo Zilkenat 7/12/2024 23:39",
		"placeTiles:inLayer:" : "Valentin Teutschbein 7/12/2024 23:37",
		"previousTileStates" : "Valentin Teutschbein 7/12/2024 14:16",
		"previousTileStates:" : "JS 7/12/2024 21:19",
		"rescaleMap" : "Ivo Zilkenat 6/24/2024 11:35",
		"resetLayers:" : "JS 7/12/2024 16:31",
		"resetTileEditChanges" : "Valentin Teutschbein 7/12/2024 23:37",
		"saveNewImageFromIndex:inLayer:" : "Ivo Zilkenat 7/12/2024 23:48",
		"savePreviousImageFromIndex:inLayer:" : "Alex M 7/12/2024 23:15",
		"saveTileEditChanges" : "Alex M 7/12/2024 23:14",
		"selectedLayers" : "JS 7/12/2024 16:55",
		"silentlyResetLayers:" : "Alex M 7/12/2024 23:26",
		"tileSelectionSet" : "jj 6/23/2024 13:35",
		"tileSelectionSet:" : "JS 7/12/2024 21:20",
		"updateTiles:inLayer:FromEvent:" : "Alex M 7/12/2024 17:14",
		"zoomAt:by:" : "Ivo Zilkenat 7/12/2024 23:47" } }
