{
	"class" : {
		"fromSpriteSheet:withColumns:andRows:" : "EB 7/20/2017 14:50",
		"fromSpriteSheet:withDimensions:" : "EB 7/13/2017 10:40" },
	"instance" : {
		"endIndex" : "MB 6/21/2017 18:18",
		"endIndex:" : "MB 6/21/2017 18:18",
		"frameCount" : "MB 6/21/2017 19:01",
		"frameTime" : "EB 6/20/2017 14:41",
		"frameTime:" : "EB 6/20/2017 14:41",
		"imageAt:" : "EB 7/13/2017 10:42",
		"looping" : "EB 6/20/2017 14:41",
		"looping:" : "EB 6/20/2017 14:41",
		"new" : "EB 6/20/2017 12:11",
		"split:" : "MB 6/21/2017 19:42",
		"splitAndStart:" : "MB 6/21/2017 13:58",
		"spriteSheet" : "EB 7/13/2017 10:41",
		"spriteSheet:" : "EB 7/13/2017 10:41",
		"startIndex" : "MB 6/21/2017 18:18",
		"startIndex:" : "MB 6/21/2017 18:18",
		"subAnimationFrom:to:" : "EB 7/22/2017 17:36",
		"totalTime" : "EB 6/20/2017 11:49",
		"transformIndex:" : "MB 6/21/2017 19:36" } }
